{
  "__inputs": [
    {
      "name": "DS_FLUX",
      "label": "Flux",
      "description": "",
      "type": "datasource",
      "pluginId": "grafana-influxdb-flux-datasource",
      "pluginName": "Flux (InfluxDB) [BETA]"
    }
  ],
  "__requires": [
    {
      "type": "grafana",
      "id": "grafana",
      "name": "Grafana",
      "version": "6.2.5"
    },
    {
      "type": "datasource",
      "id": "grafana-influxdb-flux-datasource",
      "name": "Flux (InfluxDB) [BETA]",
      "version": "5.2.11"
    },
    {
      "type": "panel",
      "id": "graph",
      "name": "Graph",
      "version": ""
    },
    {
      "type": "panel",
      "id": "table",
      "name": "Table",
      "version": ""
    }
  ],
  "annotations": {
    "list": [
      {
        "builtIn": 1,
        "datasource": "-- Grafana --",
        "enable": true,
        "hide": true,
        "iconColor": "rgba(0, 211, 255, 1)",
        "name": "Annotations & Alerts",
        "type": "dashboard"
      }
    ]
  },
  "editable": true,
  "gnetId": null,
  "graphTooltip": 0,
  "id": null,
  "iteration": 1582124699307,
  "links": [
    {
      "asDropdown": true,
      "icon": "external link",
      "keepTime": true,
      "tags": [
        "Data Access Performance"
      ],
      "title": "Related dashboards",
      "type": "dashboards"
    }
  ],
  "panels": [
    {
      "columns": [],
      "fontSize": "110%",
      "gridPos": {
        "h": 3,
        "w": 24,
        "x": 0,
        "y": 0
      },
      "id": 157,
      "links": [],
      "options": {},
      "pageSize": null,
      "scroll": false,
      "showHeader": true,
      "sort": {
        "col": 3,
        "desc": true
      },
      "styles": [
        {
          "alias": "Time",
          "dateFormat": "YYYY-MM-DD HH:mm:ss",
          "pattern": "Time",
          "type": "hidden"
        },
        {
          "alias": "",
          "colorMode": null,
          "colors": [
            "rgba(245, 54, 54, 0.9)",
            "rgba(237, 129, 40, 0.89)",
            "rgba(50, 172, 45, 0.97)"
          ],
          "dateFormat": "YYYY-MM-DD HH:mm:ss",
          "decimals": 2,
          "mappingType": 1,
          "pattern": "Measurement",
          "thresholds": [],
          "type": "hidden",
          "unit": "short"
        },
        {
          "alias": "",
          "colorMode": null,
          "colors": [
            "rgba(245, 54, 54, 0.9)",
            "rgba(237, 129, 40, 0.89)",
            "rgba(50, 172, 45, 0.97)"
          ],
          "dateFormat": "YYYY-MM-DD HH:mm:ss",
          "decimals": 2,
          "mappingType": 1,
          "pattern": "Field",
          "thresholds": [],
          "type": "hidden",
          "unit": "short"
        },
        {
          "alias": "System Failures",
          "colorMode": null,
          "colors": [
            "rgba(245, 54, 54, 0.9)",
            "rgba(237, 129, 40, 0.89)",
            "rgba(50, 172, 45, 0.97)"
          ],
          "dateFormat": "YYYY-MM-DD HH:mm:ss",
          "decimals": null,
          "mappingType": 1,
          "pattern": "b_system_errors",
          "thresholds": [],
          "type": "number",
          "unit": "locale"
        },
        {
          "alias": "Successful requests",
          "colorMode": null,
          "colors": [
            "rgba(245, 54, 54, 0.9)",
            "rgba(237, 129, 40, 0.89)",
            "rgba(50, 172, 45, 0.97)"
          ],
          "dateFormat": "YYYY-MM-DD HH:mm:ss",
          "decimals": null,
          "mappingType": 1,
          "pattern": "a_succeed_request_counter",
          "thresholds": [],
          "type": "number",
          "unit": "locale"
        },
        {
          "alias": "",
          "colorMode": null,
          "colors": [
            "rgba(245, 54, 54, 0.9)",
            "rgba(237, 129, 40, 0.89)",
            "rgba(50, 172, 45, 0.97)"
          ],
          "dateFormat": "YYYY-MM-DD HH:mm:ss",
          "decimals": 2,
          "mappingType": 1,
          "pattern": "Value",
          "thresholds": [],
          "type": "hidden",
          "unit": "short"
        },
        {
          "alias": "User Failures",
          "colorMode": null,
          "colors": [
            "rgba(245, 54, 54, 0.9)",
            "rgba(237, 129, 40, 0.89)",
            "rgba(50, 172, 45, 0.97)"
          ],
          "dateFormat": "YYYY-MM-DD HH:mm:ss",
          "decimals": null,
          "mappingType": 1,
          "pattern": "c_user_errors",
          "thresholds": [],
          "type": "number",
          "unit": "locale"
        },
        {
          "alias": "Failures % Rate",
          "colorMode": null,
          "colors": [
            "rgba(245, 54, 54, 0.9)",
            "rgba(237, 129, 40, 0.89)",
            "rgba(50, 172, 45, 0.97)"
          ],
          "dateFormat": "YYYY-MM-DD HH:mm:ss",
          "decimals": 3,
          "mappingType": 1,
          "pattern": "d_error_rate",
          "thresholds": [],
          "type": "number",
          "unit": "percentunit"
        },
        {
          "alias": "",
          "colorMode": null,
          "colors": [
            "rgba(245, 54, 54, 0.9)",
            "rgba(237, 129, 40, 0.89)",
            "rgba(50, 172, 45, 0.97)"
          ],
          "decimals": 2,
          "pattern": "/.*/",
          "thresholds": [],
          "type": "number",
          "unit": "short"
        }
      ],
      "targets": [
        {
          "query": "// need this 'default' table to substitute possibly missing sys_errors table if errors were not registered by ECS service\nimport \"csv\"\ndefault_sys_errors = csv.from(csv:\"#datatype,string,long,string,long\n#group,false,false,true,false\n#default,_result,,,\n,result,table,_field,_value\n,,100,succeed_request_counter,0\n,,101,system_errors,0\n,,102,user_errors,0\")\n\ntotals = from(bucket: \"monitoring_main\")\n|> filter(fn: (r) => r._measurement == \"statDataHead_performance_internal_transactions\" and (\"${all_hosts}\" == \"yes\" or r.host =~ /^${host:pipe}$/ ))\n|> range($range)\n|> keep(columns:[\"_time\", \"_field\", \"_value\", \"host\"])\n|> difference(nonNegative: true)\n|> drop(columns:[\"host\"])\n|> sum()\n|> fill(column: \"_value\", value: 0)\n\nsys_errors = from(bucket: \"monitoring_main\")\n|> filter(fn: (r) => r._measurement == \"statDataHead_performance_internal_error\" and (\"${all_hosts}\" == \"yes\" or r.host =~ /^${host:pipe}$/ ))\n|> range($range)\n|> keep(columns:[\"_time\", \"_field\", \"_value\", \"host\"])\n|> difference(nonNegative: true)\n|> drop(columns:[\"host\"])\n|> sum()\n|> fill(column: \"_value\", value: 0)\n\nunion(tables: [default_sys_errors, totals, sys_errors])\n|> pivot(rowKey:[], columnKey: [\"_field\"], valueColumn: \"_value\")\n// map does not save non-group columns\n|> map(fn:(r) => ({\na_succeed_request_counter: r.succeed_request_counter,\nb_system_errors: r.system_errors,\nc_user_errors: r.user_errors,\nd_error_rate: float(v:r.system_errors+r.user_errors)/\nfloat(v:r.system_errors+r.user_errors+r.succeed_request_counter\n// this trick is needed because failed+succeed can be 0, avoid printing NaN in this case\n+int(v:bool(v:(r.system_errors+r.user_errors+r.succeed_request_counter)==0)))}))\n\n",
          "refId": "A",
          "resultFormat": "table"
        }
      ],
      "title": "Transaction Summary",
      "transform": "table",
      "type": "table"
    },
    {
      "aliasColors": {},
      "bars": false,
      "dashLength": 10,
      "dashes": false,
      "decimals": null,
      "description": "Rate of successful requests and failures per second",
      "fill": 1,
      "gridPos": {
        "h": 9,
        "w": 12,
        "x": 0,
        "y": 3
      },
      "id": 147,
      "legend": {
        "alignAsTable": false,
        "avg": true,
        "current": false,
        "max": true,
        "min": true,
        "rightSide": false,
        "show": true,
        "sortDesc": true,
        "total": false,
        "values": true
      },
      "lines": true,
      "linewidth": 2,
      "links": [],
      "nullPointMode": "null",
      "options": {},
      "percentage": false,
      "pointradius": 2,
      "points": true,
      "renderer": "flot",
      "seriesOverrides": [],
      "spaceLength": 10,
      "stack": false,
      "steppedLine": false,
      "targets": [
        {
          "query": "time_int = int(v:$__range_to_s) - int(v:$__range_from_s)\nmin_window = 300\nmax_windows = 200\nsec_in_ns = 1000000000\nwindow_len = time_int / max_windows / min_window * min_window\nis_min_window = window_len < min_window\nwindow_len = (int(v:(is_min_window)) * min_window) + (int(v:(not is_min_window)) * window_len)\nwl_dur = duration(v:window_len * sec_in_ns)\nstart_dt = time(v:((int(v:$__range_from_s)/window_len) - 2) * window_len * sec_in_ns)\nend_dt = time(v:((int(v:$__range_to_s)/window_len) + 1) * window_len * sec_in_ns)\n\nfrom(bucket: \"monitoring_main\") |> filter(fn: (r) => r._measurement == \"statDataHead_performance_internal_transactions\" and r._field =~ /_request_counter$/ and (\"${all_hosts}\" == \"yes\" or r.host =~ /^${host:pipe}$/ ) )\n  |> range(start: start_dt, stop: end_dt)  \n  |> keep(columns:[\"_time\", \"_field\", \"_value\", \"host\"])  \n  |> derivative(nonNegative: true)\n  // see MONITORING-194 for details about next 2 lines\n  |> window(every:wl_dur)\n  |> mean()\n  |> drop(columns:[\"host\"]) \n  |> sum() \n  |> group(columns:[\"_field\"]) \n  |> rename(columns: {_start: \"_time\"})\n",
          "refId": "A"
        }
      ],
      "thresholds": [],
      "timeFrom": null,
      "timeRegions": [],
      "timeShift": null,
      "title": "TPS (success/failure)",
      "tooltip": {
        "shared": true,
        "sort": 0,
        "value_type": "individual"
      },
      "type": "graph",
      "xaxis": {
        "buckets": null,
        "mode": "time",
        "name": null,
        "show": true,
        "values": []
      },
      "yaxes": [
        {
          "decimals": null,
          "format": "short",
          "label": "",
          "logBase": 1,
          "max": null,
          "min": "0",
          "show": true
        },
        {
          "format": "short",
          "label": null,
          "logBase": 1,
          "max": null,
          "min": null,
          "show": true
        }
      ],
      "yaxis": {
        "align": false,
        "alignLevel": null
      }
    },
    {
      "aliasColors": {
        " total_read_requests_size": "#6ed0e0",
        " total_write_requests_size": "#e24d42"
      },
      "bars": false,
      "dashLength": 10,
      "dashes": false,
      "decimals": null,
      "description": "Data access bandwidth of successful requests per second",
      "fill": 4,
      "gridPos": {
        "h": 9,
        "w": 12,
        "x": 12,
        "y": 3
      },
      "id": 155,
      "legend": {
        "alignAsTable": false,
        "avg": true,
        "current": true,
        "max": true,
        "min": true,
        "rightSide": false,
        "show": true,
        "sortDesc": true,
        "total": false,
        "values": true
      },
      "lines": true,
      "linewidth": 2,
      "links": [],
      "nullPointMode": "null",
      "options": {},
      "percentage": false,
      "pointradius": 2,
      "points": false,
      "renderer": "flot",
      "seriesOverrides": [],
      "spaceLength": 10,
      "stack": true,
      "steppedLine": false,
      "targets": [
        {
          "query": "time_int = int(v:$__range_to_s) - int(v:$__range_from_s)\nmin_window = 300\nmax_windows = 200\nsec_in_ns = 1000000000\nwindow_len = time_int / max_windows / min_window * min_window\nis_min_window = window_len < min_window\nwindow_len = (int(v:(is_min_window)) * min_window) + (int(v:(not is_min_window)) * window_len)\nwl_dur = duration(v:window_len * sec_in_ns)\nstart_dt = time(v:((int(v:$__range_from_s)/window_len) - 2) * window_len * sec_in_ns)\nend_dt = time(v:((int(v:$__range_to_s)/window_len) + 1) * window_len * sec_in_ns)\n\nfrom(bucket: \"monitoring_main\") |> filter(fn: (r) => r._measurement == \"statDataHead_performance_internal_throughput\" and (\"${all_hosts}\" == \"yes\" or r.host =~ /^${host:pipe}$/ ) )\n  |> range(start: start_dt, stop: end_dt)  \n  |> keep(columns:[\"_time\", \"_field\", \"_value\", \"host\"])  \n  |> derivative(nonNegative: true)\n  // see MONITORING-194 for details about next 2 lines\n  |> window(every:wl_dur)\n  |> mean()\n  |> drop(columns:[\"host\"]) \n  |> sum() \n  |> group(columns:[\"_field\"]) \n  |> rename(columns: {_start: \"_time\"})\n",
          "refId": "A"
        }
      ],
      "thresholds": [],
      "timeFrom": null,
      "timeRegions": [],
      "timeShift": null,
      "title": "Bandwidth (read/write)",
      "tooltip": {
        "shared": true,
        "sort": 0,
        "value_type": "individual"
      },
      "type": "graph",
      "xaxis": {
        "buckets": null,
        "mode": "time",
        "name": null,
        "show": true,
        "values": []
      },
      "yaxes": [
        {
          "decimals": null,
          "format": "Bps",
          "label": "",
          "logBase": 1,
          "max": null,
          "min": "0",
          "show": true
        },
        {
          "format": "short",
          "label": null,
          "logBase": 1,
          "max": null,
          "min": null,
          "show": true
        }
      ],
      "yaxis": {
        "align": false,
        "alignLevel": null
      }
    },
    {
      "aliasColors": {},
      "bars": false,
      "dashLength": 10,
      "dashes": false,
      "decimals": null,
      "description": "Rate of failed requests per second, split by error type (user/system)",
      "fill": 9,
      "gridPos": {
        "h": 9,
        "w": 12,
        "x": 0,
        "y": 12
      },
      "id": 144,
      "legend": {
        "alignAsTable": false,
        "avg": true,
        "current": false,
        "hideEmpty": true,
        "hideZero": true,
        "max": true,
        "min": true,
        "rightSide": false,
        "show": true,
        "sortDesc": true,
        "total": false,
        "values": true
      },
      "lines": true,
      "linewidth": 0,
      "links": [],
      "nullPointMode": "null",
      "options": {},
      "percentage": false,
      "pointradius": 2,
      "points": false,
      "renderer": "flot",
      "seriesOverrides": [],
      "spaceLength": 10,
      "stack": true,
      "steppedLine": true,
      "targets": [
        {
          "query": "time_int = int(v:$__range_to_s) - int(v:$__range_from_s)\nmin_window = 300\nmax_windows = 200\nsec_in_ns = 1000000000\nwindow_len = time_int / max_windows / min_window * min_window\nis_min_window = window_len < min_window\nwindow_len = (int(v:(is_min_window)) * min_window) + (int(v:(not is_min_window)) * window_len)\nwl_dur = duration(v:window_len * sec_in_ns)\nstart_dt = time(v:((int(v:$__range_from_s)/window_len) - 2) * window_len * sec_in_ns)\nend_dt = time(v:((int(v:$__range_to_s)/window_len) + 1) * window_len * sec_in_ns)\n\n\nfrom(bucket: \"monitoring_main\") |> filter(fn: (r) => r._measurement == \"statDataHead_performance_internal_error\" and r._field =~ /_errors$/ and (\"${all_hosts}\" == \"yes\" or r.host =~ /^${host:pipe}$/ ))\n  |> range(start: start_dt, stop: end_dt)  \n  |> keep(columns:[\"_time\", \"_field\", \"_value\", \"host\"])  \n  |> derivative(nonNegative: true)\n  // see MONITORING-194 for details about next 2 lines\n  |> window(every:wl_dur)\n  |> mean()\n  |> drop(columns:[\"host\"]) \n  |> sum() \n  |> group(columns:[\"_field\"]) \n  |> rename(columns: {_start: \"_time\"})",
          "refId": "A"
        }
      ],
      "thresholds": [],
      "timeFrom": null,
      "timeRegions": [],
      "timeShift": null,
      "title": "Failed Requests/s by error type (user/system)",
      "tooltip": {
        "shared": true,
        "sort": 0,
        "value_type": "individual"
      },
      "type": "graph",
      "xaxis": {
        "buckets": null,
        "mode": "time",
        "name": null,
        "show": true,
        "values": []
      },
      "yaxes": [
        {
          "format": "short",
          "label": null,
          "logBase": 1,
          "max": null,
          "min": "0",
          "show": true
        },
        {
          "format": "short",
          "label": null,
          "logBase": 1,
          "max": null,
          "min": null,
          "show": true
        }
      ],
      "yaxis": {
        "align": false,
        "alignLevel": null
      }
    },
    {
      "aliasColors": {},
      "bars": false,
      "dashLength": 10,
      "dashes": false,
      "decimals": null,
      "description": "Latency of read/write requests",
      "fill": 1,
      "gridPos": {
        "h": 9,
        "w": 12,
        "x": 12,
        "y": 12
      },
      "id": 152,
      "legend": {
        "alignAsTable": false,
        "avg": true,
        "current": true,
        "max": true,
        "min": true,
        "rightSide": false,
        "show": true,
        "sortDesc": true,
        "total": false,
        "values": true
      },
      "lines": true,
      "linewidth": 2,
      "links": [],
      "nullPointMode": "null",
      "options": {},
      "percentage": false,
      "pointradius": 0.5,
      "points": true,
      "renderer": "flot",
      "seriesOverrides": [],
      "spaceLength": 10,
      "stack": false,
      "steppedLine": false,
      "targets": [
        {
          "query": "time_int = int(v:$__range_to_s) - int(v:$__range_from_s)\nmin_window = 300\nmax_windows = 200\nsec_in_ns = 1000000000\nwindow_len = time_int / max_windows / min_window * min_window\nis_min_window = window_len < min_window\nwindow_len = (int(v:(is_min_window)) * min_window) + (int(v:(not is_min_window)) * window_len)\nwl_dur = duration(v:window_len * sec_in_ns)\nstart_dt = time(v:((int(v:$__range_from_s)/window_len) - 2) * window_len * sec_in_ns)\nend_dt = time(v:((int(v:$__range_to_s)/window_len) + 1) * window_len * sec_in_ns)\n\n\na = from(bucket: \"monitoring_main\") \n    |> filter(fn: (r) => r._measurement == \"statDataHead_performance_internal_latency\" and r._field =~ /.*/ and r.id == \"ttfb_read\" and (\"${all_hosts}\" == \"yes\" or r.host =~ /^${host:pipe}$/ ) )  \n    |> range(start: start_dt, stop: end_dt)     \n    |> drop(columns:[\"_measurement\", \"process\", \"tag\"])\n    |> difference(nonNegative: true) \n    |> group(columns: [\"_field\"]) \n    |> window(every:wl_dur)     \n    |> sum()\n    |> map(fn:(r) => ({_time:r._start, le_float: float(v:r._field), cnt_float: float(v:r._value)}))\n    |> drop(columns:[\"_field\", \"_stop\"]) \n    \np50 = a |> histogramQuantile(quantile:0.50, upperBoundColumn: \"le_float\", countColumn: \"cnt_float\")\n|> rename(columns:{_start: \"_time\"})\n|> set(key: \"_field\", value: \"Read, time to first byte, p50\")\np99 = a |> histogramQuantile(quantile:0.99, upperBoundColumn: \"le_float\", countColumn: \"cnt_float\")\n|> rename(columns:{_start: \"_time\"})\n|> set(key: \"_field\", value: \"Read, time to first byte, p99\")\nunion(tables: [p50, p99])|> group(columns:[\"_field\"])\n\n",
          "refId": "A"
        },
        {
          "query": "time_int = int(v:$__range_to_s) - int(v:$__range_from_s)\nmin_window = 300\nmax_windows = 200\nsec_in_ns = 1000000000\nwindow_len = time_int / max_windows / min_window * min_window\nis_min_window = window_len < min_window\nwindow_len = (int(v:(is_min_window)) * min_window) + (int(v:(not is_min_window)) * window_len)\nwl_dur = duration(v:window_len * sec_in_ns)\nstart_dt = time(v:((int(v:$__range_from_s)/window_len) - 2) * window_len * sec_in_ns)\nend_dt = time(v:((int(v:$__range_to_s)/window_len) + 1) * window_len * sec_in_ns)\n\na = from(bucket: \"monitoring_main\") \n    |> filter(fn: (r) => r._measurement == \"statDataHead_performance_internal_latency\" and r._field =~ /.*/ and r.id == \"ttlb_write\" and (\"${all_hosts}\" == \"yes\" or r.host =~ /^${host:pipe}$/ ) )  \n    |> range(start: start_dt, stop: end_dt)     \n    |> drop(columns:[\"_measurement\", \"process\", \"tag\"])\n    |> difference(nonNegative: true) \n    |> group(columns: [\"_field\"]) \n    |> window(every:wl_dur)     \n    |> sum()\n    |> map(fn:(r) => ({_time:r._start, le_float: float(v:r._field), cnt_float: float(v:r._value)}))\n    |> drop(columns:[\"_field\", \"_stop\"]) \n    \np50 = a |> histogramQuantile(quantile:0.50, upperBoundColumn: \"le_float\", countColumn: \"cnt_float\")\n|> rename(columns:{_start: \"_time\"})\n|> set(key: \"_field\", value: \"Write, time to last byte, p50\")\np99 = a |> histogramQuantile(quantile:0.99, upperBoundColumn: \"le_float\", countColumn: \"cnt_float\")\n|> rename(columns:{_start: \"_time\"})\n|> set(key: \"_field\", value: \"Write, time to last byte, p99\")\nunion(tables: [p50, p99])|> group(columns:[\"_field\"])\n\n",
          "refId": "B"
        }
      ],
      "thresholds": [],
      "timeFrom": null,
      "timeRegions": [],
      "timeShift": null,
      "title": "Latency",
      "tooltip": {
        "shared": true,
        "sort": 0,
        "value_type": "individual"
      },
      "type": "graph",
      "xaxis": {
        "buckets": null,
        "mode": "time",
        "name": null,
        "show": true,
        "values": []
      },
      "yaxes": [
        {
          "decimals": null,
          "format": "ms",
          "label": "",
          "logBase": 1,
          "max": null,
          "min": "0",
          "show": true
        },
        {
          "format": "short",
          "label": null,
          "logBase": 1,
          "max": null,
          "min": null,
          "show": true
        }
      ],
      "yaxis": {
        "align": false,
        "alignLevel": null
      }
    },
    {
      "collapsed": true,
      "gridPos": {
        "h": 1,
        "w": 24,
        "x": 0,
        "y": 21
      },
      "id": 149,
      "panels": [
        {
          "aliasColors": {},
          "bars": false,
          "dashLength": 10,
          "dashes": false,
          "datasource": "${DS_FLUX}",
          "decimals": null,
          "description": "Rate of successful requests per second, by method",
          "fill": 9,
          "gridPos": {
            "h": 9,
            "w": 12,
            "x": 0,
            "y": 22
          },
          "id": 143,
          "legend": {
            "alignAsTable": true,
            "avg": true,
            "current": false,
            "hideEmpty": true,
            "hideZero": true,
            "max": true,
            "min": true,
            "rightSide": true,
            "show": true,
            "sort": null,
            "sortDesc": null,
            "total": false,
            "values": true
          },
          "lines": true,
          "linewidth": 0,
          "links": [],
          "nullPointMode": "null",
          "percentage": false,
          "pointradius": 2,
          "points": false,
          "renderer": "flot",
          "seriesOverrides": [],
          "spaceLength": 10,
          "stack": true,
          "steppedLine": false,
          "targets": [
            {
              "query": "time_int = int(v:$__range_to_s) - int(v:$__range_from_s)\nmin_window = 300\nmax_windows = 200\nsec_in_ns = 1000000000\nwindow_len = time_int / max_windows / min_window * min_window\nis_min_window = window_len < min_window\nwindow_len = (int(v:(is_min_window)) * min_window) + (int(v:(not is_min_window)) * window_len)\nwl_dur = duration(v:window_len * sec_in_ns)\nstart_dt = time(v:((int(v:$__range_from_s)/window_len) - 2) * window_len * sec_in_ns)\nend_dt = time(v:((int(v:$__range_to_s)/window_len) + 1) * window_len * sec_in_ns)\n\n\nfrom(bucket: \"monitoring_main\") |> filter(fn: (r) => r._measurement == \"statDataHead_performance_internal_transactions_method\" and r._field == \"succeed_request_counter\" and (\"${all_hosts}\" == \"yes\" or r.host =~ /^${host:pipe}$/ ) )\n|> range(start: start_dt, stop: end_dt) \n|> keep(columns:[\"_time\", \"_value\", \"host\", \"method\"]) \n|> derivative(nonNegative: true)\n// see MONITORING-194 for details about next 2 lines\n|> window(every:wl_dur)\n|> mean()\n|> drop(columns:[\"host\"]) \n|> sum() \n|> group(columns:[\"method\"])\n|> rename(columns: {_start: \"_time\"})\n",
              "refId": "A"
            }
          ],
          "thresholds": [],
          "timeFrom": null,
          "timeShift": null,
          "title": "Successful Requests/s by Method",
          "tooltip": {
            "shared": true,
            "sort": 0,
            "value_type": "individual"
          },
          "type": "graph",
          "xaxis": {
            "buckets": null,
            "mode": "time",
            "name": null,
            "show": true,
            "values": []
          },
          "yaxes": [
            {
              "decimals": null,
              "format": "short",
              "label": null,
              "logBase": 1,
              "max": null,
              "min": "0",
              "show": true
            },
            {
              "format": "short",
              "label": null,
              "logBase": 1,
              "max": null,
              "min": null,
              "show": true
            }
          ],
          "yaxis": {
            "align": false,
            "alignLevel": null
          }
        },
        {
          "aliasColors": {},
          "bars": false,
          "dashLength": 10,
          "dashes": false,
          "datasource": "${DS_FLUX}",
          "decimals": null,
          "description": "Rate of successful requests per second, by node",
          "fill": 9,
          "gridPos": {
            "h": 9,
            "w": 12,
            "x": 12,
            "y": 22
          },
          "id": 141,
          "legend": {
            "alignAsTable": true,
            "avg": true,
            "current": false,
            "max": true,
            "min": true,
            "rightSide": true,
            "show": true,
            "sortDesc": true,
            "total": false,
            "values": true
          },
          "lines": true,
          "linewidth": 1,
          "links": [],
          "nullPointMode": "null",
          "percentage": false,
          "pointradius": 2,
          "points": false,
          "renderer": "flot",
          "seriesOverrides": [],
          "spaceLength": 10,
          "stack": true,
          "steppedLine": false,
          "targets": [
            {
              "query": "time_int = int(v:$__range_to_s) - int(v:$__range_from_s)\nmin_window = 300\nmax_windows = 200\nsec_in_ns = 1000000000\nwindow_len = time_int / max_windows / min_window * min_window\nis_min_window = window_len < min_window\nwindow_len = (int(v:(is_min_window)) * min_window) + (int(v:(not is_min_window)) * window_len)\nwl_dur = duration(v:window_len * sec_in_ns)\nstart_dt = time(v:((int(v:$__range_from_s)/window_len) - 2) * window_len * sec_in_ns)\nend_dt = time(v:((int(v:$__range_to_s)/window_len) + 1) * window_len * sec_in_ns)\n\n\nfrom(bucket: \"monitoring_main\") |> filter(fn: (r) => r._measurement == \"statDataHead_performance_internal_transactions\" and r._field == \"succeed_request_counter\" and (\"${all_hosts}\" == \"yes\" or r.host =~ /^${host:pipe}$/ ) )\n\n|> range(start: start_dt, stop: end_dt) \n|> keep(columns:[\"_time\", \"_value\", \"host\"]) \n|> derivative(nonNegative: true)\n// see MONITORING-194 for details about next 2 lines\n|> window(every:wl_dur)\n|> mean()\n|> group(columns:[\"_field\", \"host\"]) \n|> rename(columns: {_start: \"_time\", host: \"node\"})\n\n",
              "refId": "A"
            }
          ],
          "thresholds": [],
          "timeFrom": null,
          "timeShift": null,
          "title": "Successful Requests/s by Node",
          "tooltip": {
            "shared": true,
            "sort": 0,
            "value_type": "individual"
          },
          "type": "graph",
          "xaxis": {
            "buckets": null,
            "mode": "time",
            "name": null,
            "show": true,
            "values": []
          },
          "yaxes": [
            {
              "format": "short",
              "label": null,
              "logBase": 1,
              "max": null,
              "min": null,
              "show": true
            },
            {
              "format": "short",
              "label": null,
              "logBase": 1,
              "max": null,
              "min": null,
              "show": true
            }
          ],
          "yaxis": {
            "align": false,
            "alignLevel": null
          }
        },
        {
          "aliasColors": {},
          "bars": false,
          "dashLength": 10,
          "dashes": false,
          "datasource": "${DS_FLUX}",
          "decimals": null,
          "description": "Rate of successful requests per second, by Protocol",
          "fill": 9,
          "gridPos": {
            "h": 9,
            "w": 12,
            "x": 0,
            "y": 31
          },
          "id": 153,
          "legend": {
            "alignAsTable": true,
            "avg": true,
            "current": false,
            "hideEmpty": true,
            "hideZero": true,
            "max": true,
            "min": true,
            "rightSide": true,
            "show": true,
            "sortDesc": true,
            "total": false,
            "values": true
          },
          "lines": true,
          "linewidth": 0,
          "links": [],
          "nullPointMode": "null",
          "percentage": false,
          "pointradius": 2,
          "points": false,
          "renderer": "flot",
          "seriesOverrides": [],
          "spaceLength": 10,
          "stack": true,
          "steppedLine": false,
          "targets": [
            {
              "query": "time_int = int(v:$__range_to_s) - int(v:$__range_from_s)\nmin_window = 300\nmax_windows = 200\nsec_in_ns = 1000000000\nwindow_len = time_int / max_windows / min_window * min_window\nis_min_window = window_len < min_window\nwindow_len = (int(v:(is_min_window)) * min_window) + (int(v:(not is_min_window)) * window_len)\nwl_dur = duration(v:window_len * sec_in_ns)\nstart_dt = time(v:((int(v:$__range_from_s)/window_len) - 2) * window_len * sec_in_ns)\nend_dt = time(v:((int(v:$__range_to_s)/window_len) + 1) * window_len * sec_in_ns)\n\nfrom(bucket: \"monitoring_main\") |> filter(fn: (r) => r._measurement == \"statDataHead_performance_internal_transactions_head\" and r._field == \"succeed_request_counter\" and (\"${all_hosts}\" == \"yes\" or r.host =~ /^${host:pipe}$/ ) )\n  |> range(start: start_dt, stop: end_dt)\n  |> keep(columns:[\"_time\", \"head\", \"_value\", \"host\"]) \n|> derivative(nonNegative: true)\n// see MONITORING-194 for details about next 2 lines\n|> window(every:wl_dur)\n|> mean()\n|> drop(columns:[\"host\"]) \n|> sum() \n|> group(columns:[\"head\"]) \n|> rename(columns: {_start: \"_time\", head: \"protocol\"})\n",
              "refId": "A"
            }
          ],
          "thresholds": [],
          "timeFrom": null,
          "timeShift": null,
          "title": "Successful Requests/s by Protocol",
          "tooltip": {
            "shared": true,
            "sort": 0,
            "value_type": "individual"
          },
          "type": "graph",
          "xaxis": {
            "buckets": null,
            "mode": "time",
            "name": null,
            "show": true,
            "values": []
          },
          "yaxes": [
            {
              "decimals": null,
              "format": "short",
              "label": null,
              "logBase": 1,
              "max": null,
              "min": "0",
              "show": true
            },
            {
              "format": "short",
              "label": null,
              "logBase": 1,
              "max": null,
              "min": null,
              "show": true
            }
          ],
          "yaxis": {
            "align": false,
            "alignLevel": null
          }
        }
      ],
      "title": "Successful requests drill down",
      "type": "row"
    },
    {
      "collapsed": true,
      "gridPos": {
        "h": 1,
        "w": 24,
        "x": 0,
        "y": 22
      },
      "id": 151,
      "panels": [
        {
          "aliasColors": {},
          "bars": false,
          "dashLength": 10,
          "dashes": false,
          "datasource": "${DS_FLUX}",
          "decimals": null,
          "description": "Rate of failed requests per second, split by method",
          "fill": 9,
          "gridPos": {
            "h": 9,
            "w": 12,
            "x": 0,
            "y": 23
          },
          "id": 146,
          "legend": {
            "alignAsTable": true,
            "avg": true,
            "current": false,
            "hideEmpty": true,
            "hideZero": true,
            "max": true,
            "min": true,
            "rightSide": true,
            "show": true,
            "sortDesc": true,
            "total": false,
            "values": true
          },
          "lines": true,
          "linewidth": 0,
          "links": [],
          "nullPointMode": "null",
          "percentage": false,
          "pointradius": 2,
          "points": false,
          "renderer": "flot",
          "seriesOverrides": [],
          "spaceLength": 10,
          "stack": true,
          "steppedLine": true,
          "targets": [
            {
              "query": "time_int = int(v:$__range_to_s) - int(v:$__range_from_s)\nmin_window = 300\nmax_windows = 200\nsec_in_ns = 1000000000\nwindow_len = time_int / max_windows / min_window * min_window\nis_min_window = window_len < min_window\nwindow_len = (int(v:(is_min_window)) * min_window) + (int(v:(not is_min_window)) * window_len)\nwl_dur = duration(v:window_len * sec_in_ns)\nstart_dt = time(v:((int(v:$__range_from_s)/window_len) - 2) * window_len * sec_in_ns)\nend_dt = time(v:((int(v:$__range_to_s)/window_len) + 1) * window_len * sec_in_ns)\n\n\nfrom(bucket: \"monitoring_main\") |> filter(fn: (r) => r._measurement == \"statDataHead_performance_internal_transactions_method\" and r._field == \"failed_request_counter\" and (\"${all_hosts}\" == \"yes\" or r.host =~ /^${host:pipe}$/ ))\n  |> range(start: start_dt, stop: end_dt)  \n|> keep(columns:[\"_time\", \"_value\", \"host\", \"method\"]) \n|> derivative(nonNegative: true)\n// see MONITORING-194 for details about next 2 lines\n|> window(every:wl_dur)\n|> mean()\n|> drop(columns:[\"host\"]) \n|> sum() \n|> group(columns:[\"method\"])\n|> rename(columns: {_start: \"_time\"})\n",
              "refId": "A"
            }
          ],
          "thresholds": [],
          "timeFrom": null,
          "timeShift": null,
          "title": "Failed Requests/s by Method",
          "tooltip": {
            "shared": true,
            "sort": 0,
            "value_type": "individual"
          },
          "type": "graph",
          "xaxis": {
            "buckets": null,
            "mode": "time",
            "name": null,
            "show": true,
            "values": []
          },
          "yaxes": [
            {
              "format": "short",
              "label": null,
              "logBase": 1,
              "max": null,
              "min": null,
              "show": true
            },
            {
              "format": "short",
              "label": null,
              "logBase": 1,
              "max": null,
              "min": null,
              "show": true
            }
          ],
          "yaxis": {
            "align": false,
            "alignLevel": null
          }
        },
        {
          "aliasColors": {},
          "bars": false,
          "dashLength": 10,
          "dashes": false,
          "datasource": "${DS_FLUX}",
          "decimals": null,
          "description": "Rate of failed requests per second, split by node",
          "fill": 9,
          "gridPos": {
            "h": 9,
            "w": 12,
            "x": 12,
            "y": 23
          },
          "id": 142,
          "legend": {
            "alignAsTable": true,
            "avg": true,
            "current": false,
            "hideEmpty": true,
            "hideZero": true,
            "max": true,
            "min": true,
            "rightSide": true,
            "show": true,
            "sortDesc": true,
            "total": false,
            "values": true
          },
          "lines": true,
          "linewidth": 0,
          "links": [],
          "nullPointMode": "null",
          "percentage": false,
          "pointradius": 2,
          "points": false,
          "renderer": "flot",
          "seriesOverrides": [],
          "spaceLength": 10,
          "stack": true,
          "steppedLine": true,
          "targets": [
            {
              "query": "time_int = int(v:$__range_to_s) - int(v:$__range_from_s)\nmin_window = 300\nmax_windows = 200\nsec_in_ns = 1000000000\nwindow_len = time_int / max_windows / min_window * min_window\nis_min_window = window_len < min_window\nwindow_len = (int(v:(is_min_window)) * min_window) + (int(v:(not is_min_window)) * window_len)\nwl_dur = duration(v:window_len * sec_in_ns)\nstart_dt = time(v:((int(v:$__range_from_s)/window_len) - 2) * window_len * sec_in_ns)\nend_dt = time(v:((int(v:$__range_to_s)/window_len) + 1) * window_len * sec_in_ns)\n\n\nfrom(bucket: \"monitoring_main\") |> filter(fn: (r) => r._measurement == \"statDataHead_performance_internal_transactions\" and r._field == \"failed_request_counter\" and (\"${all_hosts}\" == \"yes\" or r.host =~ /^${host:pipe}$/ ) )\n|> range(start: start_dt, stop: end_dt) \n|> keep(columns:[\"_time\", \"_value\", \"host\"]) \n|> derivative(nonNegative: true)\n// see MONITORING-194 for details about next 2 lines\n|> window(every:wl_dur)\n|> mean()\n|> group(columns:[\"_field\", \"host\"]) \n|> rename(columns: {_start: \"_time\", host: \"node\"})",
              "refId": "A"
            }
          ],
          "thresholds": [],
          "timeFrom": null,
          "timeShift": null,
          "title": "Failed Requests/s by Node",
          "tooltip": {
            "shared": true,
            "sort": 0,
            "value_type": "individual"
          },
          "type": "graph",
          "xaxis": {
            "buckets": null,
            "mode": "time",
            "name": null,
            "show": true,
            "values": []
          },
          "yaxes": [
            {
              "format": "short",
              "label": null,
              "logBase": 1,
              "max": null,
              "min": "0",
              "show": true
            },
            {
              "format": "short",
              "label": null,
              "logBase": 1,
              "max": null,
              "min": null,
              "show": true
            }
          ],
          "yaxis": {
            "align": false,
            "alignLevel": null
          }
        },
        {
          "aliasColors": {},
          "bars": false,
          "dashLength": 10,
          "dashes": false,
          "datasource": "${DS_FLUX}",
          "decimals": null,
          "description": "Rate of failed requests per second, split by Protocol",
          "fill": 9,
          "gridPos": {
            "h": 9,
            "w": 12,
            "x": 0,
            "y": 32
          },
          "id": 154,
          "legend": {
            "alignAsTable": true,
            "avg": true,
            "current": false,
            "hideEmpty": true,
            "hideZero": true,
            "max": true,
            "min": true,
            "rightSide": true,
            "show": true,
            "sortDesc": true,
            "total": false,
            "values": true
          },
          "lines": true,
          "linewidth": 0,
          "links": [],
          "nullPointMode": "null",
          "percentage": false,
          "pointradius": 2,
          "points": false,
          "renderer": "flot",
          "seriesOverrides": [],
          "spaceLength": 10,
          "stack": true,
          "steppedLine": true,
          "targets": [
            {
              "query": "time_int = int(v:$__range_to_s) - int(v:$__range_from_s)\nmin_window = 300\nmax_windows = 200\nsec_in_ns = 1000000000\nwindow_len = time_int / max_windows / min_window * min_window\nis_min_window = window_len < min_window\nwindow_len = (int(v:(is_min_window)) * min_window) + (int(v:(not is_min_window)) * window_len)\nwl_dur = duration(v:window_len * sec_in_ns)\nstart_dt = time(v:((int(v:$__range_from_s)/window_len) - 2) * window_len * sec_in_ns)\nend_dt = time(v:((int(v:$__range_to_s)/window_len) + 1) * window_len * sec_in_ns)\n\n\nfrom(bucket: \"monitoring_main\") |> filter(fn: (r) => r._measurement == \"statDataHead_performance_internal_transactions_head\" and r._field == \"failed_request_counter\" and (\"${all_hosts}\" == \"yes\" or r.host =~ /^${host:pipe}$/ ))\n  |> range(start: start_dt, stop: end_dt)\n  |> keep(columns:[\"_time\", \"head\", \"_value\", \"host\"]) \n|> derivative(nonNegative: true)\n// see MONITORING-194 for details about next 2 lines\n|> window(every:wl_dur)\n|> mean()\n|> drop(columns:[\"host\"]) \n|> sum() \n|> group(columns:[\"head\"]) \n|> rename(columns: {_start: \"_time\", head: \"protocol\"})\n",
              "refId": "A"
            }
          ],
          "thresholds": [],
          "timeFrom": null,
          "timeShift": null,
          "title": "Failed Requests/s by Protocol",
          "tooltip": {
            "shared": true,
            "sort": 0,
            "value_type": "individual"
          },
          "type": "graph",
          "xaxis": {
            "buckets": null,
            "mode": "time",
            "name": null,
            "show": true,
            "values": []
          },
          "yaxes": [
            {
              "format": "short",
              "label": null,
              "logBase": 1,
              "max": null,
              "min": null,
              "show": true
            },
            {
              "format": "short",
              "label": null,
              "logBase": 1,
              "max": null,
              "min": null,
              "show": true
            }
          ],
          "yaxis": {
            "align": false,
            "alignLevel": null
          }
        },
        {
          "aliasColors": {},
          "bars": false,
          "dashLength": 10,
          "dashes": false,
          "datasource": "${DS_FLUX}",
          "decimals": null,
          "description": "Rate of failed requests per second, split by error code",
          "fill": 10,
          "gridPos": {
            "h": 9,
            "w": 12,
            "x": 12,
            "y": 32
          },
          "id": 145,
          "legend": {
            "alignAsTable": true,
            "avg": true,
            "current": false,
            "hideEmpty": true,
            "hideZero": true,
            "max": true,
            "min": true,
            "rightSide": true,
            "show": true,
            "sortDesc": true,
            "total": false,
            "values": true
          },
          "lines": true,
          "linewidth": 0,
          "links": [],
          "nullPointMode": "null",
          "percentage": false,
          "pointradius": 2,
          "points": false,
          "renderer": "flot",
          "seriesOverrides": [],
          "spaceLength": 10,
          "stack": true,
          "steppedLine": true,
          "targets": [
            {
              "query": "time_int = int(v:$__range_to_s) - int(v:$__range_from_s)\nmin_window = 300\nmax_windows = 200\nsec_in_ns = 1000000000\nwindow_len = time_int / max_windows / min_window * min_window\nis_min_window = window_len < min_window\nwindow_len = (int(v:(is_min_window)) * min_window) + (int(v:(not is_min_window)) * window_len)\nwl_dur = duration(v:window_len * sec_in_ns)\nstart_dt = time(v:((int(v:$__range_from_s)/window_len) - 2) * window_len * sec_in_ns)\nend_dt = time(v:((int(v:$__range_to_s)/window_len) + 1) * window_len * sec_in_ns)\n\n\nfrom(bucket: \"monitoring_main\") |> filter(fn: (r) => r._measurement == \"statDataHead_performance_internal_error_code\"  and r._field == \"error_counter\" and (\"${all_hosts}\" == \"yes\" or r.host =~ /^${host:pipe}$/ ))\n  |> range(start: start_dt, stop: end_dt)\n|> keep(columns:[\"_time\", \"_value\", \"host\", \"code\"]) \n|> derivative(nonNegative: true)\n// see MONITORING-194 for details about next 2 lines\n|> window(every:wl_dur)\n|> mean()\n|> drop(columns:[\"host\"]) \n|> sum() \n|> group(columns:[\"code\"])\n|> rename(columns: {_start: \"_time\"})\n\n",
              "refId": "A"
            }
          ],
          "thresholds": [],
          "timeFrom": null,
          "timeShift": null,
          "title": "Failed Requests/s by error code",
          "tooltip": {
            "shared": true,
            "sort": 0,
            "value_type": "individual"
          },
          "type": "graph",
          "xaxis": {
            "buckets": null,
            "mode": "time",
            "name": null,
            "show": true,
            "values": []
          },
          "yaxes": [
            {
              "format": "short",
              "label": null,
              "logBase": 1,
              "max": null,
              "min": "0",
              "show": true
            },
            {
              "format": "short",
              "label": null,
              "logBase": 1,
              "max": null,
              "min": null,
              "show": true
            }
          ],
          "yaxis": {
            "align": false,
            "alignLevel": null
          }
        }
      ],
      "title": "Failures drill down",
      "type": "row"
    },
    {
      "collapsed": true,
      "gridPos": {
        "h": 1,
        "w": 24,
        "x": 0,
        "y": 23
      },
      "id": 161,
      "panels": [
        {
          "aliasColors": {},
          "bars": false,
          "dashLength": 10,
          "dashes": false,
          "datasource": "${DS_FLUX}",
          "decimals": null,
          "description": "Select multiple nodes and compare rates of successful requests per second",
          "fill": 1,
          "gridPos": {
            "h": 9,
            "w": 12,
            "x": 0,
            "y": 24
          },
          "id": 162,
          "legend": {
            "alignAsTable": false,
            "avg": true,
            "current": false,
            "max": true,
            "min": true,
            "rightSide": false,
            "show": true,
            "sortDesc": true,
            "total": false,
            "values": true
          },
          "lines": true,
          "linewidth": 2,
          "links": [],
          "nullPointMode": "null",
          "percentage": false,
          "pointradius": 2,
          "points": true,
          "renderer": "flot",
          "seriesOverrides": [],
          "spaceLength": 10,
          "stack": false,
          "steppedLine": false,
          "targets": [
            {
              "query": "time_int = int(v:$__range_to_s) - int(v:$__range_from_s)\nmin_window = 300\nmax_windows = 200\nsec_in_ns = 1000000000\nwindow_len = time_int / max_windows / min_window * min_window\nis_min_window = window_len < min_window\nwindow_len = (int(v:(is_min_window)) * min_window) + (int(v:(not is_min_window)) * window_len)\nwl_dur = duration(v:window_len * sec_in_ns)\nstart_dt = time(v:((int(v:$__range_from_s)/window_len) - 2) * window_len * sec_in_ns)\nend_dt = time(v:((int(v:$__range_to_s)/window_len) + 1) * window_len * sec_in_ns)\n\nfrom(bucket: \"monitoring_main\") |> filter(fn: (r) => r._measurement == \"statDataHead_performance_internal_transactions\" and r._field =~ /succeed_request_counter$/ and (\"${all_hosts}\" == \"yes\" or r.host =~ /^${host:pipe}$/ ) )\n  |> range(start: start_dt, stop: end_dt)  \n  |> keep(columns:[\"_time\", \"_field\", \"_value\", \"host\"])  \n  |> derivative(nonNegative: true)\n  // see MONITORING-194 for details about next 2 lines\n  |> window(every:wl_dur)\n  |> mean()\n  |> group(columns:[\"_field\", \"host\"]) \n  |> rename(columns: {_start: \"_time\", host: \"node\"})\n",
              "refId": "A"
            }
          ],
          "thresholds": [],
          "timeFrom": null,
          "timeShift": null,
          "title": "Compare TPS of success requests",
          "tooltip": {
            "shared": true,
            "sort": 0,
            "value_type": "individual"
          },
          "transparent": false,
          "type": "graph",
          "xaxis": {
            "buckets": null,
            "mode": "time",
            "name": null,
            "show": true,
            "values": []
          },
          "yaxes": [
            {
              "decimals": null,
              "format": "short",
              "label": "",
              "logBase": 1,
              "max": null,
              "min": "0",
              "show": true
            },
            {
              "format": "short",
              "label": null,
              "logBase": 1,
              "max": null,
              "min": null,
              "show": true
            }
          ],
          "yaxis": {
            "align": false,
            "alignLevel": null
          }
        },
        {
          "aliasColors": {},
          "bars": false,
          "dashLength": 10,
          "dashes": false,
          "datasource": "${DS_FLUX}",
          "decimals": null,
          "description": "Select multiple nodes and compare rates of failed requests per second, split by error type (user/system)",
          "fill": 1,
          "gridPos": {
            "h": 9,
            "w": 12,
            "x": 12,
            "y": 24
          },
          "id": 164,
          "legend": {
            "alignAsTable": false,
            "avg": true,
            "current": false,
            "hideEmpty": true,
            "hideZero": true,
            "max": true,
            "min": true,
            "rightSide": false,
            "show": true,
            "sortDesc": true,
            "total": false,
            "values": true
          },
          "lines": true,
          "linewidth": 2,
          "links": [],
          "nullPointMode": "null",
          "percentage": false,
          "pointradius": 0.5,
          "points": true,
          "renderer": "flot",
          "seriesOverrides": [],
          "spaceLength": 10,
          "stack": false,
          "steppedLine": false,
          "targets": [
            {
              "query": "time_int = int(v:$__range_to_s) - int(v:$__range_from_s)\nmin_window = 300\nmax_windows = 200\nsec_in_ns = 1000000000\nwindow_len = time_int / max_windows / min_window * min_window\nis_min_window = window_len < min_window\nwindow_len = (int(v:(is_min_window)) * min_window) + (int(v:(not is_min_window)) * window_len)\nwl_dur = duration(v:window_len * sec_in_ns)\nstart_dt = time(v:((int(v:$__range_from_s)/window_len) - 2) * window_len * sec_in_ns)\nend_dt = time(v:((int(v:$__range_to_s)/window_len) + 1) * window_len * sec_in_ns)\n\n\nfrom(bucket: \"monitoring_main\") |> filter(fn: (r) => r._measurement == \"statDataHead_performance_internal_error\" and r._field =~ /_errors$/ and (\"${all_hosts}\" == \"yes\" or r.host =~ /^${host:pipe}$/ ))\n  |> range(start: start_dt, stop: end_dt)  \n  |> keep(columns:[\"_time\", \"_field\", \"_value\", \"host\"])  \n  |> derivative(nonNegative: true)\n  // see MONITORING-194 for details about next 2 lines\n  |> window(every:wl_dur)\n  |> mean()\n  |> group(columns:[\"_field\", \"host\"]) \n  |> rename(columns: {_start: \"_time\", host: \"node\"})",
              "refId": "A"
            }
          ],
          "thresholds": [],
          "timeFrom": null,
          "timeShift": null,
          "title": "Compare rate of failed requests/s",
          "tooltip": {
            "shared": true,
            "sort": 0,
            "value_type": "individual"
          },
          "type": "graph",
          "xaxis": {
            "buckets": null,
            "mode": "time",
            "name": null,
            "show": true,
            "values": []
          },
          "yaxes": [
            {
              "format": "short",
              "label": null,
              "logBase": 1,
              "max": null,
              "min": "0",
              "show": true
            },
            {
              "format": "short",
              "label": null,
              "logBase": 1,
              "max": null,
              "min": null,
              "show": true
            }
          ],
          "yaxis": {
            "align": false,
            "alignLevel": null
          }
        },
        {
          "aliasColors": {},
          "bars": false,
          "dashLength": 10,
          "dashes": false,
          "datasource": "${DS_FLUX}",
          "decimals": null,
          "description": "Select multiple nodes and compare data access bandwidth of successful requests per second",
          "fill": 1,
          "gridPos": {
            "h": 9,
            "w": 12,
            "x": 0,
            "y": 33
          },
          "id": 163,
          "legend": {
            "alignAsTable": false,
            "avg": true,
            "current": true,
            "max": true,
            "min": true,
            "rightSide": false,
            "show": true,
            "sortDesc": true,
            "total": false,
            "values": true
          },
          "lines": true,
          "linewidth": 2,
          "links": [],
          "nullPointMode": "null",
          "percentage": false,
          "pointradius": 2,
          "points": true,
          "renderer": "flot",
          "seriesOverrides": [],
          "spaceLength": 10,
          "stack": false,
          "steppedLine": false,
          "targets": [
            {
              "query": "time_int = int(v:$__range_to_s) - int(v:$__range_from_s)\nmin_window = 300\nmax_windows = 200\nsec_in_ns = 1000000000\nwindow_len = time_int / max_windows / min_window * min_window\nis_min_window = window_len < min_window\nwindow_len = (int(v:(is_min_window)) * min_window) + (int(v:(not is_min_window)) * window_len)\nwl_dur = duration(v:window_len * sec_in_ns)\nstart_dt = time(v:((int(v:$__range_from_s)/window_len) - 2) * window_len * sec_in_ns)\nend_dt = time(v:((int(v:$__range_to_s)/window_len) + 1) * window_len * sec_in_ns)\n\nfrom(bucket: \"monitoring_main\") |> filter(fn: (r) => r._measurement == \"statDataHead_performance_internal_throughput\" and r._field == \"total_read_requests_size\" and (\"${all_hosts}\" == \"yes\" or r.host =~ /^${host:pipe}$/ ) )\n  |> range(start: start_dt, stop: end_dt)  \n  |> keep(columns:[\"_time\", \"_field\", \"_value\", \"host\"])  \n  |> derivative(nonNegative: true)\n  // see MONITORING-194 for details about next 2 lines\n  |> window(every:wl_dur)\n  |> mean()\n  |> group(columns:[\"_field\", \"host\"]) \n  |> rename(columns: {_start: \"_time\", host: \"node\"})\n",
              "refId": "A"
            }
          ],
          "thresholds": [],
          "timeFrom": null,
          "timeShift": null,
          "title": "Compare read bandwidth",
          "tooltip": {
            "shared": true,
            "sort": 0,
            "value_type": "individual"
          },
          "transparent": false,
          "type": "graph",
          "xaxis": {
            "buckets": null,
            "mode": "time",
            "name": null,
            "show": true,
            "values": []
          },
          "yaxes": [
            {
              "decimals": null,
              "format": "Bps",
              "label": "",
              "logBase": 1,
              "max": null,
              "min": "0",
              "show": true
            },
            {
              "format": "short",
              "label": null,
              "logBase": 1,
              "max": null,
              "min": null,
              "show": true
            }
          ],
          "yaxis": {
            "align": false,
            "alignLevel": null
          }
        },
        {
          "aliasColors": {},
          "bars": false,
          "dashLength": 10,
          "dashes": false,
          "datasource": "${DS_FLUX}",
          "decimals": null,
          "description": "Select multiple nodes and compare data access bandwidth of successful requests per second",
          "fill": 1,
          "gridPos": {
            "h": 9,
            "w": 12,
            "x": 12,
            "y": 33
          },
          "id": 166,
          "legend": {
            "alignAsTable": false,
            "avg": true,
            "current": true,
            "max": true,
            "min": true,
            "rightSide": false,
            "show": true,
            "sortDesc": true,
            "total": false,
            "values": true
          },
          "lines": true,
          "linewidth": 2,
          "links": [],
          "nullPointMode": "null",
          "percentage": false,
          "pointradius": 2,
          "points": true,
          "renderer": "flot",
          "seriesOverrides": [],
          "spaceLength": 10,
          "stack": false,
          "steppedLine": false,
          "targets": [
            {
              "query": "time_int = int(v:$__range_to_s) - int(v:$__range_from_s)\nmin_window = 300\nmax_windows = 200\nsec_in_ns = 1000000000\nwindow_len = time_int / max_windows / min_window * min_window\nis_min_window = window_len < min_window\nwindow_len = (int(v:(is_min_window)) * min_window) + (int(v:(not is_min_window)) * window_len)\nwl_dur = duration(v:window_len * sec_in_ns)\nstart_dt = time(v:((int(v:$__range_from_s)/window_len) - 2) * window_len * sec_in_ns)\nend_dt = time(v:((int(v:$__range_to_s)/window_len) + 1) * window_len * sec_in_ns)\n\nfrom(bucket: \"monitoring_main\") |> filter(fn: (r) => r._measurement == \"statDataHead_performance_internal_throughput\" and r._field == \"total_write_requests_size\" and (\"${all_hosts}\" == \"yes\" or r.host =~ /^${host:pipe}$/ ) )\n  |> range(start: start_dt, stop: end_dt)  \n  |> keep(columns:[\"_time\", \"_field\", \"_value\", \"host\"])  \n  |> derivative(nonNegative: true)\n  // see MONITORING-194 for details about next 2 lines\n  |> window(every:wl_dur)\n  |> mean()\n  |> group(columns:[\"_field\", \"host\"]) \n  |> rename(columns: {_start: \"_time\", host: \"node\"})\n",
              "refId": "A"
            }
          ],
          "thresholds": [],
          "timeFrom": null,
          "timeShift": null,
          "title": "Compare write bandwidth",
          "tooltip": {
            "shared": true,
            "sort": 0,
            "value_type": "individual"
          },
          "transparent": false,
          "type": "graph",
          "xaxis": {
            "buckets": null,
            "mode": "time",
            "name": null,
            "show": true,
            "values": []
          },
          "yaxes": [
            {
              "decimals": null,
              "format": "Bps",
              "label": "",
              "logBase": 1,
              "max": null,
              "min": "0",
              "show": true
            },
            {
              "format": "short",
              "label": null,
              "logBase": 1,
              "max": null,
              "min": null,
              "show": true
            }
          ],
          "yaxis": {
            "align": false,
            "alignLevel": null
          }
        },
        {
          "aliasColors": {},
          "bars": false,
          "dashLength": 10,
          "dashes": false,
          "datasource": "${DS_FLUX}",
          "decimals": null,
          "description": "Select multiple nodes and compare latency of read requests",
          "fill": 1,
          "gridPos": {
            "h": 9,
            "w": 12,
            "x": 0,
            "y": 42
          },
          "id": 165,
          "legend": {
            "alignAsTable": false,
            "avg": true,
            "current": true,
            "max": true,
            "min": true,
            "rightSide": false,
            "show": true,
            "sortDesc": true,
            "total": false,
            "values": true
          },
          "lines": true,
          "linewidth": 2,
          "links": [],
          "nullPointMode": "null",
          "percentage": false,
          "pointradius": 0.5,
          "points": true,
          "renderer": "flot",
          "seriesOverrides": [],
          "spaceLength": 10,
          "stack": false,
          "steppedLine": false,
          "targets": [
            {
              "query": "time_int = int(v:$__range_to_s) - int(v:$__range_from_s)\nmin_window = 300\nmax_windows = 200\nsec_in_ns = 1000000000\nwindow_len = time_int / max_windows / min_window * min_window\nis_min_window = window_len < min_window\nwindow_len = (int(v:(is_min_window)) * min_window) + (int(v:(not is_min_window)) * window_len)\nwl_dur = duration(v:window_len * sec_in_ns)\nstart_dt = time(v:((int(v:$__range_from_s)/window_len) - 2) * window_len * sec_in_ns)\nend_dt = time(v:((int(v:$__range_to_s)/window_len) + 1) * window_len * sec_in_ns)\n\n\na = from(bucket: \"monitoring_main\") \n    |> filter(fn: (r) => r._measurement == \"statDataHead_performance_internal_latency\" and r.id == \"ttfb_read\" and (\"${all_hosts}\" == \"yes\" or r.host =~ /^${host:pipe}$/ ) )  \n    |> range(start: start_dt, stop: end_dt)     \n    |> drop(columns:[\"_measurement\", \"process\", \"tag\"])\n    |> difference(nonNegative: true) \n    |> group(columns: [\"_field\", \"host\"]) \n    |> window(every:wl_dur)     \n    |> sum()\n    |> map(fn:(r) => ({_time:r._start, le_float: float(v:r._field), cnt_float: float(v:r._value)}))\n    |> drop(columns:[\"_field\", \"_stop\"]) \n    \np50 = a |> histogramQuantile(quantile:0.50, upperBoundColumn: \"le_float\", countColumn: \"cnt_float\")\n|> rename(columns:{_start: \"_time\"})\n|> set(key: \"_field\", value: \"Read, time to first byte, p50\")\np99 = a |> histogramQuantile(quantile:0.99, upperBoundColumn: \"le_float\", countColumn: \"cnt_float\")\n|> rename(columns:{_start: \"_time\"})\n|> set(key: \"_field\", value: \"Read, time to first byte, p99\")\nunion(tables: [p50, p99])|> group(columns:[\"_field\", \"host\"])\n\n",
              "refId": "A"
            }
          ],
          "thresholds": [],
          "timeFrom": null,
          "timeShift": null,
          "title": "Compare read latency",
          "tooltip": {
            "shared": true,
            "sort": 0,
            "value_type": "individual"
          },
          "transparent": false,
          "type": "graph",
          "xaxis": {
            "buckets": null,
            "mode": "time",
            "name": null,
            "show": true,
            "values": []
          },
          "yaxes": [
            {
              "decimals": null,
              "format": "ms",
              "label": "",
              "logBase": 1,
              "max": null,
              "min": "0",
              "show": true
            },
            {
              "format": "short",
              "label": null,
              "logBase": 1,
              "max": null,
              "min": null,
              "show": true
            }
          ],
          "yaxis": {
            "align": false,
            "alignLevel": null
          }
        },
        {
          "aliasColors": {},
          "bars": false,
          "dashLength": 10,
          "dashes": false,
          "datasource": "${DS_FLUX}",
          "decimals": null,
          "description": "Select multiple nodes and compare latency of write requests",
          "fill": 1,
          "gridPos": {
            "h": 9,
            "w": 12,
            "x": 12,
            "y": 42
          },
          "id": 167,
          "legend": {
            "alignAsTable": false,
            "avg": true,
            "current": true,
            "max": true,
            "min": true,
            "rightSide": false,
            "show": true,
            "sortDesc": true,
            "total": false,
            "values": true
          },
          "lines": true,
          "linewidth": 2,
          "links": [],
          "nullPointMode": "null",
          "percentage": false,
          "pointradius": 0.5,
          "points": true,
          "renderer": "flot",
          "seriesOverrides": [],
          "spaceLength": 10,
          "stack": false,
          "steppedLine": false,
          "targets": [
            {
              "query": "time_int = int(v:$__range_to_s) - int(v:$__range_from_s)\nmin_window = 300\nmax_windows = 200\nsec_in_ns = 1000000000\nwindow_len = time_int / max_windows / min_window * min_window\nis_min_window = window_len < min_window\nwindow_len = (int(v:(is_min_window)) * min_window) + (int(v:(not is_min_window)) * window_len)\nwl_dur = duration(v:window_len * sec_in_ns)\nstart_dt = time(v:((int(v:$__range_from_s)/window_len) - 2) * window_len * sec_in_ns)\nend_dt = time(v:((int(v:$__range_to_s)/window_len) + 1) * window_len * sec_in_ns)\n\n\na = from(bucket: \"monitoring_main\") \n    |> filter(fn: (r) => r._measurement == \"statDataHead_performance_internal_latency\" and r.id == \"ttlb_write\" and (\"${all_hosts}\" == \"yes\" or r.host =~ /^${host:pipe}$/ ) )  \n    |> range(start: start_dt, stop: end_dt)     \n    |> drop(columns:[\"_measurement\", \"process\", \"tag\"])\n    |> difference(nonNegative: true) \n    |> group(columns: [\"_field\", \"host\"]) \n    |> window(every:wl_dur)     \n    |> sum()\n    |> map(fn:(r) => ({_time:r._start, le_float: float(v:r._field), cnt_float: float(v:r._value)}))\n    |> drop(columns:[\"_field\", \"_stop\"]) \n    \np50 = a |> histogramQuantile(quantile:0.50, upperBoundColumn: \"le_float\", countColumn: \"cnt_float\")\n|> rename(columns:{_start: \"_time\"})\n|> set(key: \"_field\", value: \"Write, time to last byte, p50\")\np99 = a |> histogramQuantile(quantile:0.99, upperBoundColumn: \"le_float\", countColumn: \"cnt_float\")\n|> rename(columns:{_start: \"_time\"})\n|> set(key: \"_field\", value: \"Write, time to last byte, p99\")\nunion(tables: [p50, p99])|> group(columns:[\"_field\", \"host\"])\n\n\n\n",
              "refId": "A"
            }
          ],
          "thresholds": [],
          "timeFrom": null,
          "timeShift": null,
          "title": "Compare write latency",
          "tooltip": {
            "shared": true,
            "sort": 0,
            "value_type": "individual"
          },
          "transparent": false,
          "type": "graph",
          "xaxis": {
            "buckets": null,
            "mode": "time",
            "name": null,
            "show": true,
            "values": []
          },
          "yaxes": [
            {
              "decimals": null,
              "format": "ms",
              "label": "",
              "logBase": 1,
              "max": null,
              "min": "0",
              "show": true
            },
            {
              "format": "short",
              "label": null,
              "logBase": 1,
              "max": null,
              "min": null,
              "show": true
            }
          ],
          "yaxis": {
            "align": false,
            "alignLevel": null
          }
        }
      ],
      "title": "Compare: select multiple nodes",
      "type": "row"
    }
  ],
  "refresh": false,
  "schemaVersion": 18,
  "style": "dark",
  "tags": [
    "Data Access Performance"
  ],
  "templating": {
    "list": [
      {
        "allValue": ".*",
        "current": {},
        "datasource": "${DS_FLUX}",
        "definition": "from(bucket:\"monitoring_main\")     |> range(start: -60m)     |> filter(fn:(r) => r._measurement == \"statDataHead_performance_internal_transactions\" )     |> group(columns:[\"host\"])     |> distinct(column:\"host\")",
        "hide": 0,
        "includeAll": false,
        "label": "Node",
        "multi": true,
        "name": "host",
        "options": [],
        "query": "from(bucket:\"monitoring_main\")     |> range(start: -60m)     |> filter(fn:(r) => r._measurement == \"statDataHead_performance_internal_transactions\" )     |> group(columns:[\"host\"])     |> distinct(column:\"host\")",
        "refresh": 1,
        "regex": "",
        "skipUrlSync": false,
        "sort": 5,
        "tagValuesQuery": "",
        "tags": [],
        "tagsQuery": "",
        "type": "query",
        "useTags": false
      },
      {
        "allValue": null,
        "current": {
          "tags": [],
          "text": "no",
          "value": "no"
        },
        "hide": 2,
        "includeAll": false,
        "label": "Show all nodes (experimental)",
        "multi": false,
        "name": "all_hosts",
        "options": [
          {
            "selected": true,
            "text": "no",
            "value": "no"
          },
          {
            "selected": false,
            "text": "yes",
            "value": "yes"
          }
        ],
        "query": "no,yes",
        "skipUrlSync": false,
        "type": "custom"
      }
    ]
  },
  "time": {
    "from": "now-24h",
    "to": "now"
  },
  "timepicker": {
    "refresh_intervals": [
      "5s",
      "10s",
      "30s",
      "1m",
      "5m",
      "15m",
      "30m",
      "1h",
      "2h",
      "1d"
    ],
    "time_options": [
      "5m",
      "15m",
      "1h",
      "6h",
      "12h",
      "24h",
      "2d",
      "7d",
      "30d"
    ]
  },
  "timezone": "",
  "title": "Data Access Performance - by Nodes",
  "uid": "kRnHd7eiz",
  "version": 2
}